README.md
setup.cfg
setup.py
dsnd_probability_ec/Binomialdistribution.py
dsnd_probability_ec/Gaussiandistribution.py
dsnd_probability_ec/Generaldistribution.py
dsnd_probability_ec/__init__.py
dsnd_probability_ec.egg-info/PKG-INFO
dsnd_probability_ec.egg-info/SOURCES.txt
dsnd_probability_ec.egg-info/dependency_links.txt
dsnd_probability_ec.egg-info/not-zip-safe
dsnd_probability_ec.egg-info/top_level.txt